paramcheckup/__init__.py
paramcheckup/data_frames.py
paramcheckup/documentation.py
paramcheckup/numbers.py
paramcheckup/numpy_arrays.py
paramcheckup/parameters.py
paramcheckup/types.py
paramcheckup/utils.py
paramcheckup/version.py
paramcheckup-1.0.3.dist-info/LICENSE
paramcheckup-1.0.3.dist-info/METADATA
paramcheckup-1.0.3.dist-info/WHEEL
paramcheckup-1.0.3.dist-info/top_level.txt
paramcheckup-1.0.3.dist-info/RECORD
