Metadata-Version: 2.1
Name: paramcheckup
Version: 1.0.3
Summary: Check whether the parameters received are correct
Author-email: Anderson Marcos Dias Canteli <andersonmdcanteli@gmail.com>
License: BSD 3-Clause License
Project-URL: Source, https://github.com/puzzle-in-a-mug/paramcheckup
Project-URL: Docs, https://paramcheckup.readthedocs.io/en/latest/
Keywords: type,check,warnings
Classifier: Development Status :: 3 - Alpha
Classifier: Intended Audience :: Developers
Classifier: License :: OSI Approved :: BSD License
Classifier: Operating System :: OS Independent
Classifier: Programming Language :: Python :: 3 :: Only
Classifier: Programming Language :: Python :: 3.10
Classifier: Programming Language :: Python :: 3.11
Classifier: Programming Language :: Python :: 3.12
Requires-Python: >=3.10
License-File: LICENSE
Requires-Dist: numpy >=1.23.5
Requires-Dist: pandas >=1.5.3
Requires-Dist: matplotlib >=3.7.1
